{
    "id": 90342772,
    "name": "Ballin",
    "author": "JodyCondor",
    "creators": ["JodyCondor"],
    "verifier": "JodyCondor",
    "verification": "https://youtu.be/o_VByeJEXJ4",
    "percentToQualify": "100",
    "password": "",
    "records": [

        {
            "user": "Lily",
            "link": "",
            "percent": 100,
            "hz": 69
       },
        {
            "user": "DiamondSword216",
            "link": "",
            "percent": 100,
            "hz": 69
       }
        
    ]
}
